redditJson/__init__.py
redditJson/example.py
redditJson-0.0.11.dist-info/LICENSE
redditJson-0.0.11.dist-info/METADATA
redditJson-0.0.11.dist-info/WHEEL
redditJson-0.0.11.dist-info/top_level.txt
redditJson-0.0.11.dist-info/RECORD
